line.py
count_line-0.1.2.dist-info/METADATA
count_line-0.1.2.dist-info/RECORD
count_line-0.1.2.dist-info/WHEEL
count_line-0.1.2.dist-info/entry_points.txt
count_line-0.1.2.dist-info/top_level.txt
