Metadata-Version: 2.1
Name: count-line
Version: 0.1.2
Summary: A command line tool to count lines and files numbers under current directory.
Home-page: https://github.com/hj24/count-line
Author: hj24
Author-email: mambahj24@gmail.com
License: MIT
Platform: UNKNOWN
Classifier: License :: OSI Approved :: MIT License
Classifier: Programming Language :: Python
Classifier: Programming Language :: Python :: 3
Classifier: Programming Language :: Python :: 3.6
Classifier: Programming Language :: Python :: Implementation :: CPython
Classifier: Programming Language :: Python :: Implementation :: PyPy
Requires-Python: >=3
